README.md
setup.py
awsLexAlexa/__init__.py
awsLexAlexa/event_handler.py
awsLexAlexa.egg-info/PKG-INFO
awsLexAlexa.egg-info/SOURCES.txt
awsLexAlexa.egg-info/dependency_links.txt
awsLexAlexa.egg-info/top_level.txt
awsLexAlexa/events/__init__.py
awsLexAlexa/events/alexaEvent.py
awsLexAlexa/events/eventInterface.py
awsLexAlexa/events/lexEvent.py
awsLexAlexa/logs/__init__.py
awsLexAlexa/logs/configLogs.py