Metadata-Version: 2.1
Name: awsLexAlexa
Version: 0.9
Summary: UNKNOWN
Home-page: https://github.com/dmmop/awsLexAlexa
Author: David Martinez Martin
Author-email: davidmtn@gmail.com
License: GNU General Public License v3
Platform: UNKNOWN
Classifier: Programming Language :: Python :: 3
Classifier: Development Status :: 5 - Production/Stable
Classifier: Topic :: Utilities
Classifier: License :: OSI Approved :: GNU General Public License v3 or later (GPLv3+)
Classifier: Operating System :: OS Independent
